{"P6": {"labels": ["documentation"], "postTitle": "\u5bf9\u7b49\u4fdd2.0\u7684\u7406\u89e3", "postUrl": "post/dui-deng-bao-2.0-de-li-jie.html", "createdDate": "2025-12-01", "dateLabelColor": "#0969da"}, "P5": {"labels": ["documentation"], "postTitle": "UDP\u548cTCP53\u7aef\u53e3\u7684\u533a\u522b", "postUrl": "post/UDP-he-TCP53-duan-kou-de-qu-bie.html", "createdDate": "2025-12-01", "dateLabelColor": "#0969da"}, "P4": {"labels": ["documentation"], "postTitle": "VM\u6709\u4e0d\u540c\u7f51\u5361\u7684\u539f\u56e0", "postUrl": "post/VM-you-bu-tong-wang-qia-de-yuan-yin.html", "createdDate": "2025-12-01", "dateLabelColor": "#0969da"}, "P3": {"labels": ["documentation"], "postTitle": "VM\u51fa\u73b0\u4e0d\u540c\u7f51\u5361\u7684\u539f\u56e0", "postUrl": "post/VM-chu-xian-bu-tong-wang-qia-de-yuan-yin.html", "createdDate": "2025-12-01", "dateLabelColor": "#0969da"}, "P2": {"labels": ["documentation"], "postTitle": "\u641c\u7d22\u5f15\u64ce\u548c\u5b50\u57df\u540d\u6536\u96c6", "postUrl": "post/sou-suo-yin-qing-he-zi-yu-ming-shou-ji.html", "createdDate": "2025-11-26", "dateLabelColor": "#0969da"}, "P1": {"labels": ["documentation"], "postTitle": "whireshak\u6293\u5305", "postUrl": "post/whireshak-zhua-bao.html", "createdDate": "2025-11-26", "dateLabelColor": "#0969da"}, "labelColorDict": {"bug": "#d73a4a", "documentation": "#0075ca", "duplicate": "#cfd3d7", "enhancement": "#a2eeef", "good first issue": "#7057ff", "help wanted": "#008672", "invalid": "#e4e669", "question": "#d876e3", "wontfix": "#ffffff"}}